{
  "branch": "CSE",
  "year": "2",
  "section": "B",
  "attendance_dates": {
    "from": "20-01-2025",
    "to": "23-04-2025"
  },
  "students": [
    {
      "sno": "1",
      "htno": "23891A0565",
      "name": "AMBATI SIDDHARTHA",
      "subjects": {
        "DM": "29",
        "BEFA": "32",
        "OS": "34",
        "DBMS": "38",
        "SE": "20",
        "OS LAB": "27",
        "DBMS LAB": "14",
        "NODE JS": "29",
        "COI": "2",
        "REAL TIME PROJECT": "0",
        "CRT": "46"
      },
      "total": "271",
      "percentage": "63.92"
    },
    {
      "sno": "2",
      "htno": "23891A0566",
      "name": "ANTHATI SANJAY",
      "subjects": {
        "DM": "25",
        "BEFA": "21",
        "OS": "27",
        "DBMS": "20",
        "SE": "16",
        "OS LAB": "15",
        "DBMS LAB": "13",
        "NODE JS": "25",
        "COI": "1",
        "REAL TIME PROJECT": "0",
        "CRT": "31"
      },
      "total": "194",
      "percentage": "45.75"
    },
    {
      "sno": "3",
      "htno": "23891A0567",
      "name": "ANTHATI UDAYASRI",
      "subjects": {
        "DM": "41",
        "BEFA": "32",
        "OS": "40",
        "DBMS": "49",
        "SE": "34",
        "OS LAB": "20",
        "DBMS LAB": "31",
        "NODE JS": "34",
        "COI": "2",
        "REAL TIME PROJECT": "0",
        "CRT": "57"
      },
      "total": "340",
      "percentage": "80.19"
    },
    {
      "sno": "4",
      "htno": "23891A0568",
      "name": "BADDAM YASHWANTH",
      "subjects": {
        "DM": "41",
        "BEFA": "30",
        "OS": "38",
        "DBMS": "50",
        "SE": "33",
        "OS LAB": "21",
        "DBMS LAB": "27",
        "NODE JS": "31",
        "COI": "2",
        "REAL TIME PROJECT": "0",
        "CRT": "50"
      },
      "total": "323",
      "percentage": "76.18"
    },
    {
      "sno": "5",
      "htno": "23891A0569",
      "name": "BAKANAGARI MEGHANA",
      "subjects": {
        "DM": "48",
        "BEFA": "38",
        "OS": "44",
        "DBMS": "56",
        "SE": "37",
        "OS LAB": "29",
        "DBMS LAB": "35",
        "NODE JS": "30",
        "COI": "2",
        "REAL TIME PROJECT": "0",
        "CRT": "60"
      },
      "total": "379",
      "percentage": "89.39"
    },
    {
      "sno": "6",
      "htno": "23891A0570",
      "name": "BANOTHU ANJALI",
      "subjects": {
        "DM": "30",
        "BEFA": "22",
        "OS": "21",
        "DBMS": "31",
        "SE": "18",
        "OS LAB": "23",
        "DBMS LAB": "26",
        "NODE JS": "15",
        "COI": "2",
        "REAL TIME PROJECT": "0",
        "CRT": "40"
      },
      "total": "228",
      "percentage": "53.77"
    },
    {
      "sno": "7",
      "htno": "23891A0571",
      "name": "BATHULA GEETHANJALI",
      "subjects": {
        "DM": "35",
        "BEFA": "27",
        "OS": "27",
        "DBMS": "36",
        "SE": "25",
        "OS LAB": "25",
        "DBMS LAB": "24",
        "NODE JS": "21",
        "COI": "2",
        "REAL TIME PROJECT": "0",
        "CRT": "41"
      },
      "total": "263",
      "percentage": "62.03"
    },
    {
      "sno": "8",
      "htno": "23891A0572",
      "name": "BEJJAM SIDDARTHA",
      "subjects": {
        "DM": "35",
        "BEFA": "33",
        "OS": "39",
        "DBMS": "39",
        "SE": "23",
        "OS LAB": "27",
        "DBMS LAB": "25",
        "NODE JS": "26",
        "COI": "2",
        "REAL TIME PROJECT": "0",
        "CRT": "57"
      },
      "total": "306",
      "percentage": "72.17"
    },
    {
      "sno": "9",
      "htno": "23891A0573",
      "name": "BODDU BHANU PRASAD",
      "subjects": {
        "DM": "38",
        "BEFA": "27",
        "OS": "36",
        "DBMS": "35",
        "SE": "24",
        "OS LAB": "26",
        "DBMS LAB": "30",
        "NODE JS": "30",
        "COI": "2",
        "REAL TIME PROJECT": "0",
        "CRT": "48"
      },
      "total": "296",
      "percentage": "69.81"
    },
    {
      "sno": "10",
      "htno": "23891A0574",
      "name": "BOLLAM ARAVIND",
      "subjects": {
        "DM": "40",
        "BEFA": "29",
        "OS": "36",
        "DBMS": "46",
        "SE": "27",
        "OS LAB": "29",
        "DBMS LAB": "29",
        "NODE JS": "28",
        "COI": "0",
        "REAL TIME PROJECT": "0",
        "CRT": "53"
      },
      "total": "317",
      "percentage": "74.76"
    },
    {
      "sno": "11",
      "htno": "23891A0575",
      "name": "BURRA VENKATA PAVAN KALYAN",
      "subjects": {
        "DM": "47",
        "BEFA": "33",
        "OS": "40",
        "DBMS": "52",
        "SE": "30",
        "OS LAB": "29",
        "DBMS LAB": "32",
        "NODE JS": "30",
        "COI": "2",
        "REAL TIME PROJECT": "0",
        "CRT": "62"
      },
      "total": "357",
      "percentage": "84.2"
    },
    {
      "sno": "12",
      "htno": "23891A0576",
      "name": "CHOLLETI SAI SATHWIK",
      "subjects": {
        "DM": "39",
        "BEFA": "30",
        "OS": "37",
        "DBMS": "46",
        "SE": "32",
        "OS LAB": "27",
        "DBMS LAB": "28",
        "NODE JS": "31",
        "COI": "0",
        "REAL TIME PROJECT": "0",
        "CRT": "56"
      },
      "total": "326",
      "percentage": "76.89"
    },
    {
      "sno": "13",
      "htno": "23891A0577",
      "name": "DEETI JASMITHA",
      "subjects": {
        "DM": "44",
        "BEFA": "33",
        "OS": "37",
        "DBMS": "45",
        "SE": "26",
        "OS LAB": "29",
        "DBMS LAB": "28",
        "NODE JS": "30",
        "COI": "2",
        "REAL TIME PROJECT": "0",
        "CRT": "50"
      },
      "total": "324",
      "percentage": "76.42"
    },
    {
      "sno": "14",
      "htno": "23891A0578",
      "name": "DHARAVATH SRILATHA",
      "subjects": {
        "DM": "46",
        "BEFA": "36",
        "OS": "42",
        "DBMS": "55",
        "SE": "30",
        "OS LAB": "27",
        "DBMS LAB": "32",
        "NODE JS": "31",
        "COI": "2",
        "REAL TIME PROJECT": "0",
        "CRT": "57"
      },
      "total": "358",
      "percentage": "84.43"
    },
    {
      "sno": "15",
      "htno": "23891A0579",
      "name": "DHOLLU KRISHNA VAMSHI",
      "subjects": {
        "DM": "40",
        "BEFA": "35",
        "OS": "41",
        "DBMS": "50",
        "SE": "28",
        "OS LAB": "24",
        "DBMS LAB": "32",
        "NODE JS": "33",
        "COI": "2",
        "REAL TIME PROJECT": "0",
        "CRT": "51"
      },
      "total": "336",
      "percentage": "79.25"
    },
    {
      "sno": "16",
      "htno": "23891A0580",
      "name": "DOTI SANDHYA RANI",
      "subjects": {
        "DM": "48",
        "BEFA": "40",
        "OS": "46",
        "DBMS": "58",
        "SE": "34",
        "OS LAB": "26",
        "DBMS LAB": "34",
        "NODE JS": "35",
        "COI": "3",
        "REAL TIME PROJECT": "0",
        "CRT": "64"
      },
      "total": "388",
      "percentage": "91.51"
    },
    {
      "sno": "17",
      "htno": "23891A0581",
      "name": "DUPPELLI VARSHITHA",
      "subjects": {
        "DM": "43",
        "BEFA": "32",
        "OS": "42",
        "DBMS": "49",
        "SE": "31",
        "OS LAB": "26",
        "DBMS LAB": "32",
        "NODE JS": "31",
        "COI": "1",
        "REAL TIME PROJECT": "0",
        "CRT": "64"
      },
      "total": "351",
      "percentage": "82.78"
    },
    {
      "sno": "18",
      "htno": "23891A0582",
      "name": "EEDA SUSHMA",
      "subjects": {
        "DM": "47",
        "BEFA": "39",
        "OS": "45",
        "DBMS": "56",
        "SE": "30",
        "OS LAB": "32",
        "DBMS LAB": "31",
        "NODE JS": "29",
        "COI": "3",
        "REAL TIME PROJECT": "0",
        "CRT": "63"
      },
      "total": "375",
      "percentage": "88.44"
    },
    {
      "sno": "19",
      "htno": "23891A0583",
      "name": "G JAIDEEP",
      "subjects": {
        "DM": "42",
        "BEFA": "30",
        "OS": "39",
        "DBMS": "42",
        "SE": "22",
        "OS LAB": "24",
        "DBMS LAB": "33",
        "NODE JS": "31",
        "COI": "2",
        "REAL TIME PROJECT": "0",
        "CRT": "57"
      },
      "total": "322",
      "percentage": "75.94"
    },
    {
      "sno": "20",
      "htno": "23891A0585",
      "name": "GHANTASALA RAMA KOUSALYA",
      "subjects": {
        "DM": "52",
        "BEFA": "45",
        "OS": "48",
        "DBMS": "61",
        "SE": "35",
        "OS LAB": "32",
        "DBMS LAB": "35",
        "NODE JS": "31",
        "COI": "5",
        "REAL TIME PROJECT": "0",
        "CRT": "67"
      },
      "total": "411",
      "percentage": "96.93"
    },
    {
      "sno": "21",
      "htno": "23891A0586",
      "name": "GOLLA DASARI SHIVA KUMAR",
      "subjects": {
        "DM": "39",
        "BEFA": "32",
        "OS": "35",
        "DBMS": "44",
        "SE": "28",
        "OS LAB": "26",
        "DBMS LAB": "27",
        "NODE JS": "32",
        "COI": "1",
        "REAL TIME PROJECT": "0",
        "CRT": "49"
      },
      "total": "313",
      "percentage": "73.82"
    },
    {
      "sno": "22",
      "htno": "23891A0587",
      "name": "GUNDAY SRISHANTH GOUD",
      "subjects": {
        "DM": "36",
        "BEFA": "30",
        "OS": "42",
        "DBMS": "40",
        "SE": "20",
        "OS LAB": "29",
        "DBMS LAB": "28",
        "NODE JS": "34",
        "COI": "1",
        "REAL TIME PROJECT": "0",
        "CRT": "56"
      },
      "total": "316",
      "percentage": "74.53"
    },
    {
      "sno": "23",
      "htno": "23891A0588",
      "name": "GURJAPALLI SRUJAN ANIRUDH",
      "subjects": {
        "DM": "36",
        "BEFA": "31",
        "OS": "38",
        "DBMS": "38",
        "SE": "26",
        "OS LAB": "24",
        "DBMS LAB": "24",
        "NODE JS": "27",
        "COI": "2",
        "REAL TIME PROJECT": "0",
        "CRT": "54"
      },
      "total": "300",
      "percentage": "70.75"
    },
    {
      "sno": "24",
      "htno": "23891A0589",
      "name": "HANMANTHU SWATHI",
      "subjects": {
        "DM": "45",
        "BEFA": "32",
        "OS": "38",
        "DBMS": "53",
        "SE": "32",
        "OS LAB": "26",
        "DBMS LAB": "35",
        "NODE JS": "22",
        "COI": "2",
        "REAL TIME PROJECT": "0",
        "CRT": "57"
      },
      "total": "342",
      "percentage": "80.66"
    },
    {
      "sno": "25",
      "htno": "23891A0591",
      "name": "JEEVALA NAEEM SIDDIQ",
      "subjects": {
        "DM": "37",
        "BEFA": "32",
        "OS": "28",
        "DBMS": "39",
        "SE": "19",
        "OS LAB": "22",
        "DBMS LAB": "27",
        "NODE JS": "24",
        "COI": "3",
        "REAL TIME PROJECT": "0",
        "CRT": "43"
      },
      "total": "274",
      "percentage": "64.62"
    },
    {
      "sno": "26",
      "htno": "23891A0592",
      "name": "K JOHARIKA",
      "subjects": {
        "DM": "46",
        "BEFA": "38",
        "OS": "47",
        "DBMS": "54",
        "SE": "30",
        "OS LAB": "24",
        "DBMS LAB": "31",
        "NODE JS": "34",
        "COI": "4",
        "REAL TIME PROJECT": "0",
        "CRT": "58"
      },
      "total": "366",
      "percentage": "86.32"
    },
    {
      "sno": "27",
      "htno": "23891A0593",
      "name": "KANAPALA CHAITANYA TEJA",
      "subjects": {
        "DM": "39",
        "BEFA": "28",
        "OS": "36",
        "DBMS": "39",
        "SE": "29",
        "OS LAB": "27",
        "DBMS LAB": "28",
        "NODE JS": "28",
        "COI": "0",
        "REAL TIME PROJECT": "0",
        "CRT": "55"
      },
      "total": "309",
      "percentage": "72.88"
    },
    {
      "sno": "28",
      "htno": "23891A0594",
      "name": "KANNAVENI SHIRISHA",
      "subjects": {
        "DM": "44",
        "BEFA": "36",
        "OS": "42",
        "DBMS": "51",
        "SE": "34",
        "OS LAB": "24",
        "DBMS LAB": "32",
        "NODE JS": "32",
        "COI": "4",
        "REAL TIME PROJECT": "0",
        "CRT": "53"
      },
      "total": "352",
      "percentage": "83.02"
    },
    {
      "sno": "29",
      "htno": "23891A0595",
      "name": "KAVALA PAVAN KUMAR",
      "subjects": {
        "DM": "37",
        "BEFA": "26",
        "OS": "36",
        "DBMS": "46",
        "SE": "26",
        "OS LAB": "29",
        "DBMS LAB": "28",
        "NODE JS": "28",
        "COI": "1",
        "REAL TIME PROJECT": "0",
        "CRT": "48"
      },
      "total": "305",
      "percentage": "71.93"
    },
    {
      "sno": "30",
      "htno": "23891A0596",
      "name": "KOMMU SRINIVAS",
      "subjects": {
        "DM": "41",
        "BEFA": "28",
        "OS": "39",
        "DBMS": "49",
        "SE": "32",
        "OS LAB": "24",
        "DBMS LAB": "29",
        "NODE JS": "31",
        "COI": "0",
        "REAL TIME PROJECT": "0",
        "CRT": "59"
      },
      "total": "332",
      "percentage": "78.3"
    },
    {
      "sno": "31",
      "htno": "23891A0597",
      "name": "KOTHA SATHWIK REDDY",
      "subjects": {
        "DM": "34",
        "BEFA": "29",
        "OS": "33",
        "DBMS": "48",
        "SE": "30",
        "OS LAB": "29",
        "DBMS LAB": "25",
        "NODE JS": "19",
        "COI": "1",
        "REAL TIME PROJECT": "0",
        "CRT": "45"
      },
      "total": "293",
      "percentage": "69.1"
    },
    {
      "sno": "32",
      "htno": "23891A0598",
      "name": "KOTHA SHASHANK GOUD",
      "subjects": {
        "DM": "43",
        "BEFA": "38",
        "OS": "42",
        "DBMS": "50",
        "SE": "31",
        "OS LAB": "26",
        "DBMS LAB": "29",
        "NODE JS": "32",
        "COI": "2",
        "REAL TIME PROJECT": "0",
        "CRT": "60"
      },
      "total": "353",
      "percentage": "83.25"
    },
    {
      "sno": "33",
      "htno": "23891A0599",
      "name": "LINGADAPU BALA PRANEETH",
      "subjects": {
        "DM": "46",
        "BEFA": "36",
        "OS": "43",
        "DBMS": "54",
        "SE": "32",
        "OS LAB": "29",
        "DBMS LAB": "32",
        "NODE JS": "34",
        "COI": "3",
        "REAL TIME PROJECT": "0",
        "CRT": "64"
      },
      "total": "373",
      "percentage": "87.97"
    },
    {
      "sno": "34",
      "htno": "23891A05A0",
      "name": "MAADU CHATHURYA",
      "subjects": {
        "DM": "48",
        "BEFA": "37",
        "OS": "42",
        "DBMS": "50",
        "SE": "31",
        "OS LAB": "32",
        "DBMS LAB": "28",
        "NODE JS": "34",
        "COI": "3",
        "REAL TIME PROJECT": "0",
        "CRT": "57"
      },
      "total": "362",
      "percentage": "85.38"
    },
    {
      "sno": "35",
      "htno": "23891A05A1",
      "name": "MAHENDRA ABHIGHNA",
      "subjects": {
        "DM": "42",
        "BEFA": "27",
        "OS": "36",
        "DBMS": "45",
        "SE": "28",
        "OS LAB": "26",
        "DBMS LAB": "32",
        "NODE JS": "28",
        "COI": "3",
        "REAL TIME PROJECT": "0",
        "CRT": "46"
      },
      "total": "313",
      "percentage": "73.82"
    },
    {
      "sno": "36",
      "htno": "23891A05A2",
      "name": "MALOTHU RAJKUMAR",
      "subjects": {
        "DM": "42",
        "BEFA": "32",
        "OS": "39",
        "DBMS": "46",
        "SE": "31",
        "OS LAB": "23",
        "DBMS LAB": "27",
        "NODE JS": "31",
        "COI": "3",
        "REAL TIME PROJECT": "0",
        "CRT": "50"
      },
      "total": "324",
      "percentage": "76.42"
    },
    {
      "sno": "37",
      "htno": "23891A05A3",
      "name": "MEMULA NAGA PRANEETH",
      "subjects": {
        "DM": "43",
        "BEFA": "33",
        "OS": "42",
        "DBMS": "51",
        "SE": "25",
        "OS LAB": "28",
        "DBMS LAB": "29",
        "NODE JS": "34",
        "COI": "2",
        "REAL TIME PROJECT": "0",
        "CRT": "54"
      },
      "total": "341",
      "percentage": "80.42"
    },
    {
      "sno": "38",
      "htno": "23891A05A4",
      "name": "MUDAVATH VINOD",
      "subjects": {
        "DM": "41",
        "BEFA": "35",
        "OS": "40",
        "DBMS": "42",
        "SE": "28",
        "OS LAB": "29",
        "DBMS LAB": "24",
        "NODE JS": "31",
        "COI": "4",
        "REAL TIME PROJECT": "0",
        "CRT": "46"
      },
      "total": "320",
      "percentage": "75.47"
    },
    {
      "sno": "39",
      "htno": "23891A05A5",
      "name": "MUDDAM SHIVA PRASAD",
      "subjects": {
        "DM": "47",
        "BEFA": "36",
        "OS": "45",
        "DBMS": "56",
        "SE": "34",
        "OS LAB": "26",
        "DBMS LAB": "32",
        "NODE JS": "34",
        "COI": "3",
        "REAL TIME PROJECT": "0",
        "CRT": "64"
      },
      "total": "377",
      "percentage": "88.92"
    },
    {
      "sno": "40",
      "htno": "23891A05A6",
      "name": "MUNJAMPALLY TEJDEEP",
      "subjects": {
        "DM": "48",
        "BEFA": "38",
        "OS": "47",
        "DBMS": "59",
        "SE": "35",
        "OS LAB": "27",
        "DBMS LAB": "34",
        "NODE JS": "35",
        "COI": "3",
        "REAL TIME PROJECT": "0",
        "CRT": "68"
      },
      "total": "394",
      "percentage": "92.92"
    },
    {
      "sno": "41",
      "htno": "23891A05A7",
      "name": "MUTAKODURU SAI KOUSHIK",
      "subjects": {
        "DM": "35",
        "BEFA": "34",
        "OS": "40",
        "DBMS": "42",
        "SE": "27",
        "OS LAB": "29",
        "DBMS LAB": "11",
        "NODE JS": "34",
        "COI": "3",
        "REAL TIME PROJECT": "0",
        "CRT": "47"
      },
      "total": "302",
      "percentage": "71.23"
    },
    {
      "sno": "42",
      "htno": "23891A05A8",
      "name": "MUTUPURI SOUMYA",
      "subjects": {
        "DM": "39",
        "BEFA": "26",
        "OS": "34",
        "DBMS": "38",
        "SE": "23",
        "OS LAB": "29",
        "DBMS LAB": "32",
        "NODE JS": "31",
        "COI": "2",
        "REAL TIME PROJECT": "0",
        "CRT": "43"
      },
      "total": "297",
      "percentage": "70.05"
    },
    {
      "sno": "43",
      "htno": "23891A05A9",
      "name": "NAKKA DHARANI GOUD",
      "subjects": {
        "DM": "43",
        "BEFA": "39",
        "OS": "44",
        "DBMS": "52",
        "SE": "34",
        "OS LAB": "24",
        "DBMS LAB": "32",
        "NODE JS": "31",
        "COI": "5",
        "REAL TIME PROJECT": "0",
        "CRT": "62"
      },
      "total": "366",
      "percentage": "86.32"
    },
    {
      "sno": "44",
      "htno": "23891A05B0",
      "name": "NARABOINA RAJESH",
      "subjects": {
        "DM": "44",
        "BEFA": "28",
        "OS": "37",
        "DBMS": "44",
        "SE": "29",
        "OS LAB": "26",
        "DBMS LAB": "30",
        "NODE JS": "28",
        "COI": "2",
        "REAL TIME PROJECT": "0",
        "CRT": "52"
      },
      "total": "320",
      "percentage": "75.47"
    },
    {
      "sno": "45",
      "htno": "23891A05B1",
      "name": "NEMANANDAM SINDHU",
      "subjects": {
        "DM": "42",
        "BEFA": "33",
        "OS": "36",
        "DBMS": "51",
        "SE": "28",
        "OS LAB": "25",
        "DBMS LAB": "35",
        "NODE JS": "17",
        "COI": "3",
        "REAL TIME PROJECT": "0",
        "CRT": "54"
      },
      "total": "324",
      "percentage": "76.42"
    },
    {
      "sno": "46",
      "htno": "23891A05B2",
      "name": "NENAVATH NEERAJA",
      "subjects": {
        "DM": "41",
        "BEFA": "36",
        "OS": "43",
        "DBMS": "52",
        "SE": "29",
        "OS LAB": "29",
        "DBMS LAB": "32",
        "NODE JS": "31",
        "COI": "2",
        "REAL TIME PROJECT": "0",
        "CRT": "67"
      },
      "total": "362",
      "percentage": "85.38"
    },
    {
      "sno": "47",
      "htno": "23891A05B3",
      "name": "PANDIRI JAYENDRA VENKATA GOPALA KRISHNA",
      "subjects": {
        "DM": "32",
        "BEFA": "32",
        "OS": "40",
        "DBMS": "35",
        "SE": "26",
        "OS LAB": "27",
        "DBMS LAB": "26",
        "NODE JS": "28",
        "COI": "2",
        "REAL TIME PROJECT": "0",
        "CRT": "50"
      },
      "total": "298",
      "percentage": "70.28"
    },
    {
      "sno": "48",
      "htno": "23891A05B4",
      "name": "PANNALA ANUSHA",
      "subjects": {
        "DM": "42",
        "BEFA": "34",
        "OS": "43",
        "DBMS": "49",
        "SE": "32",
        "OS LAB": "24",
        "DBMS LAB": "29",
        "NODE JS": "34",
        "COI": "2",
        "REAL TIME PROJECT": "0",
        "CRT": "59"
      },
      "total": "348",
      "percentage": "82.08"
    },
    {
      "sno": "49",
      "htno": "23891A05B5",
      "name": "PATLOLLA PRANEETH REDDY",
      "subjects": {
        "DM": "35",
        "BEFA": "32",
        "OS": "35",
        "DBMS": "47",
        "SE": "29",
        "OS LAB": "28",
        "DBMS LAB": "27",
        "NODE JS": "33",
        "COI": "2",
        "REAL TIME PROJECT": "0",
        "CRT": "46"
      },
      "total": "314",
      "percentage": "74.06"
    },
    {
      "sno": "50",
      "htno": "23891A05B6",
      "name": "PILLEM RAHUL",
      "subjects": {
        "DM": "46",
        "BEFA": "40",
        "OS": "47",
        "DBMS": "57",
        "SE": "34",
        "OS LAB": "29",
        "DBMS LAB": "29",
        "NODE JS": "34",
        "COI": "3",
        "REAL TIME PROJECT": "0",
        "CRT": "63"
      },
      "total": "382",
      "percentage": "90.09"
    },
    {
      "sno": "51",
      "htno": "23891A05B7",
      "name": "PINJARY MAHESH KUMAR",
      "subjects": {
        "DM": "35",
        "BEFA": "26",
        "OS": "34",
        "DBMS": "38",
        "SE": "28",
        "OS LAB": "26",
        "DBMS LAB": "23",
        "NODE JS": "28",
        "COI": "1",
        "REAL TIME PROJECT": "0",
        "CRT": "39"
      },
      "total": "278",
      "percentage": "65.57"
    },
    {
      "sno": "52",
      "htno": "23891A05B8",
      "name": "POREDDY AKSHAYA",
      "subjects": {
        "DM": "46",
        "BEFA": "37",
        "OS": "46",
        "DBMS": "55",
        "SE": "33",
        "OS LAB": "32",
        "DBMS LAB": "31",
        "NODE JS": "31",
        "COI": "2",
        "REAL TIME PROJECT": "0",
        "CRT": "64"
      },
      "total": "377",
      "percentage": "88.92"
    },
    {
      "sno": "53",
      "htno": "23891A05B9",
      "name": "PUSULURI SANMITHA",
      "subjects": {
        "DM": "44",
        "BEFA": "34",
        "OS": "42",
        "DBMS": "50",
        "SE": "30",
        "OS LAB": "24",
        "DBMS LAB": "29",
        "NODE JS": "32",
        "COI": "3",
        "REAL TIME PROJECT": "0",
        "CRT": "57"
      },
      "total": "345",
      "percentage": "81.37"
    },
    {
      "sno": "54",
      "htno": "23891A05C0",
      "name": "SAI BHARGAVI SAGARALA",
      "subjects": {
        "DM": "44",
        "BEFA": "35",
        "OS": "43",
        "DBMS": "53",
        "SE": "31",
        "OS LAB": "24",
        "DBMS LAB": "26",
        "NODE JS": "31",
        "COI": "4",
        "REAL TIME PROJECT": "0",
        "CRT": "52"
      },
      "total": "343",
      "percentage": "80.9"
    },
    {
      "sno": "55",
      "htno": "23891A05C1",
      "name": "SAMBODHI AGNIMITHRA",
      "subjects": {
        "DM": "14",
        "BEFA": "11",
        "OS": "18",
        "DBMS": "10",
        "SE": "15",
        "OS LAB": "15",
        "DBMS LAB": "3",
        "NODE JS": "9",
        "COI": "0",
        "REAL TIME PROJECT": "0",
        "CRT": "18"
      },
      "total": "113",
      "percentage": "26.65"
    },
    {
      "sno": "56",
      "htno": "23891A05C2",
      "name": "SHAIK SAMEERA",
      "subjects": {
        "DM": "36",
        "BEFA": "28",
        "OS": "35",
        "DBMS": "40",
        "SE": "26",
        "OS LAB": "25",
        "DBMS LAB": "22",
        "NODE JS": "31",
        "COI": "0",
        "REAL TIME PROJECT": "0",
        "CRT": "56"
      },
      "total": "299",
      "percentage": "70.52"
    },
    {
      "sno": "57",
      "htno": "23891A05C3",
      "name": "SHAIK SANIA JASMINE",
      "subjects": {
        "DM": "45",
        "BEFA": "37",
        "OS": "47",
        "DBMS": "52",
        "SE": "32",
        "OS LAB": "24",
        "DBMS LAB": "31",
        "NODE JS": "34",
        "COI": "3",
        "REAL TIME PROJECT": "0",
        "CRT": "65"
      },
      "total": "370",
      "percentage": "87.26"
    },
    {
      "sno": "58",
      "htno": "23891A05C4",
      "name": "SIDDELA PAVAN",
      "subjects": {
        "DM": "36",
        "BEFA": "32",
        "OS": "38",
        "DBMS": "42",
        "SE": "26",
        "OS LAB": "32",
        "DBMS LAB": "20",
        "NODE JS": "26",
        "COI": "2",
        "REAL TIME PROJECT": "0",
        "CRT": "44"
      },
      "total": "298",
      "percentage": "70.28"
    },
    {
      "sno": "59",
      "htno": "23891A05C5",
      "name": "SOMA DEVISRI PRASAD",
      "subjects": {
        "DM": "40",
        "BEFA": "29",
        "OS": "40",
        "DBMS": "46",
        "SE": "28",
        "OS LAB": "32",
        "DBMS LAB": "32",
        "NODE JS": "31",
        "COI": "0",
        "REAL TIME PROJECT": "0",
        "CRT": "62"
      },
      "total": "340",
      "percentage": "80.19"
    },
    {
      "sno": "60",
      "htno": "23891A05C6",
      "name": "THATIKONDA SRIKANTH",
      "subjects": {
        "DM": "31",
        "BEFA": "29",
        "OS": "31",
        "DBMS": "39",
        "SE": "25",
        "OS LAB": "25",
        "DBMS LAB": "24",
        "NODE JS": "25",
        "COI": "3",
        "REAL TIME PROJECT": "0",
        "CRT": "37"
      },
      "total": "269",
      "percentage": "63.44"
    },
    {
      "sno": "61",
      "htno": "23891A05C7",
      "name": "TRISHITHA GUNDLA",
      "subjects": {
        "DM": "36",
        "BEFA": "29",
        "OS": "40",
        "DBMS": "41",
        "SE": "21",
        "OS LAB": "29",
        "DBMS LAB": "28",
        "NODE JS": "34",
        "COI": "1",
        "REAL TIME PROJECT": "0",
        "CRT": "55"
      },
      "total": "314",
      "percentage": "74.06"
    },
    {
      "sno": "62",
      "htno": "23891A05C8",
      "name": "VADDAMANU PRADEEP KUMAR",
      "subjects": {
        "DM": "38",
        "BEFA": "31",
        "OS": "35",
        "DBMS": "47",
        "SE": "28",
        "OS LAB": "32",
        "DBMS LAB": "30",
        "NODE JS": "31",
        "COI": "0",
        "REAL TIME PROJECT": "0",
        "CRT": "50"
      },
      "total": "322",
      "percentage": "75.94"
    },
    {
      "sno": "63",
      "htno": "24895A0507",
      "name": "KUKKA TRIVENI",
      "subjects": {
        "DM": "40",
        "BEFA": "26",
        "OS": "34",
        "DBMS": "45",
        "SE": "26",
        "OS LAB": "26",
        "DBMS LAB": "29",
        "NODE JS": "25",
        "COI": "1",
        "REAL TIME PROJECT": "0",
        "CRT": "45"
      },
      "total": "297",
      "percentage": "70.05"
    },
    {
      "sno": "64",
      "htno": "24895A0508",
      "name": "KOLA RASAGNA",
      "subjects": {
        "DM": "35",
        "BEFA": "27",
        "OS": "26",
        "DBMS": "38",
        "SE": "24",
        "OS LAB": "17",
        "DBMS LAB": "24",
        "NODE JS": "25",
        "COI": "3",
        "REAL TIME PROJECT": "0",
        "CRT": "32"
      },
      "total": "251",
      "percentage": "59.2"
    },
    {
      "sno": "65",
      "htno": "24895A0509",
      "name": "AILA NAVYA SRI",
      "subjects": {
        "DM": "31",
        "BEFA": "25",
        "OS": "29",
        "DBMS": "37",
        "SE": "18",
        "OS LAB": "20",
        "DBMS LAB": "26",
        "NODE JS": "23",
        "COI": "0",
        "REAL TIME PROJECT": "0",
        "CRT": "42"
      },
      "total": "251",
      "percentage": "59.2"
    },
    {
      "sno": "66",
      "htno": "24895A0510",
      "name": "GUMMULA SOUMYA",
      "subjects": {
        "DM": "41",
        "BEFA": "30",
        "OS": "38",
        "DBMS": "48",
        "SE": "28",
        "OS LAB": "26",
        "DBMS LAB": "32",
        "NODE JS": "29",
        "COI": "1",
        "REAL TIME PROJECT": "0",
        "CRT": "50"
      },
      "total": "323",
      "percentage": "76.18"
    },
    {
      "sno": "67",
      "htno": "24895A0511",
      "name": "KATHULA SRIKANTH",
      "subjects": {
        "DM": "34",
        "BEFA": "24",
        "OS": "30",
        "DBMS": "41",
        "SE": "22",
        "OS LAB": "26",
        "DBMS LAB": "27",
        "NODE JS": "25",
        "COI": "0",
        "REAL TIME PROJECT": "0",
        "CRT": "44"
      },
      "total": "273",
      "percentage": "64.39"
    },
    {
      "sno": "68",
      "htno": "24895A0512",
      "name": "GONE SHIVA KRISHNA",
      "subjects": {
        "DM": "40",
        "BEFA": "24",
        "OS": "36",
        "DBMS": "43",
        "SE": "28",
        "OS LAB": "27",
        "DBMS LAB": "23",
        "NODE JS": "30",
        "COI": "0",
        "REAL TIME PROJECT": "0",
        "CRT": "46"
      },
      "total": "297",
      "percentage": "70.05"
    }
  ]
}